README.md
setup.py
semba/__init__.py
semba/algebra.py
semba/default_priors.py
semba/inspector.py
semba/matrix_variate_normal.py
semba/model.py
semba/model_effects.py
semba/model_means.py
semba/model_mixin.py
semba/plot.py
semba/solver.py
semba.egg-info/PKG-INFO
semba.egg-info/SOURCES.txt
semba.egg-info/dependency_links.txt
semba.egg-info/requires.txt
semba.egg-info/top_level.txt