Metadata-Version: 2.1
Name: semba
Version: 0.9
Summary: Bayesian  Structural Equation Modeling 
Home-page: https://bayes.semopy.com
Author: Georgy Meshcheryakov
Author-email: metsheryakov_ga@spbstu.ru
License: UNKNOWN
Platform: UNKNOWN
Classifier: Programming Language :: Python :: 3.7
Classifier: Programming Language :: Python :: 3.8
Classifier: Programming Language :: Python :: 3.9
Classifier: Programming Language :: Python :: 3.10
Classifier: License :: OSI Approved :: MIT License
Classifier: Development Status :: 3 - Alpha
Classifier: Topic :: Scientific/Engineering
Classifier: Operating System :: OS Independent
Requires-Python: >=3.7
